transformer_vae/__init__.py
transformer_vae/__main__.py
transformer_vae/autoencoders.py
transformer_vae/config.py
transformer_vae/data_collator.py
transformer_vae/metrics.py
transformer_vae/model.py
transformer_vae/model_outputs.py
transformer_vae/sequence_checks.py
transformer_vae/sklearn.py
transformer_vae/train.py
transformer_vae/trainer.py
transformer_vae/trainer_callback.py
transformer_vae/utils.py
transformer_vae-0.0.2.dist-info/LICENSE
transformer_vae-0.0.2.dist-info/METADATA
transformer_vae-0.0.2.dist-info/WHEEL
transformer_vae-0.0.2.dist-info/top_level.txt
transformer_vae-0.0.2.dist-info/RECORD
