Metadata-Version: 2.1
Name: transformer-vae
Version: 0.0.2
Summary: Interpolate between discrete sequences.
Home-page: https://github.com/Fraser-Greenlee/transformer-vae
Author: Fraser Greenlee
Author-email: fraser.greenlee@mac.com
License: MIT
Platform: UNKNOWN
Classifier: Programming Language :: Python :: 3
Classifier: License :: OSI Approved :: MIT License
Classifier: Operating System :: OS Independent
Requires-Python: >=3.6
Requires-Dist: datasets (==1.1.3)
Requires-Dist: transformers (==4.1.1)
Requires-Dist: wandb (>=0.10.12)
Requires-Dist: torch (==1.7.0)
Requires-Dist: sklearn
Requires-Dist: bert-score
Provides-Extra: test
Requires-Dist: pytest ; extra == 'test'
Requires-Dist: flake8 ; extra == 'test'
Requires-Dist: flake8-mypy ; extra == 'test'
Requires-Dist: black ; extra == 'test'
Requires-Dist: twine ; extra == 'test'
